runner/__init__.py
runner/runner.py
cch_runner-0.1.0.dist-info/WHEEL
cch_runner-0.1.0.dist-info/METADATA
cch_runner-0.1.0.dist-info/RECORD
