Metadata-Version: 2.1
Name: cch-runner
Version: 0.1.0
Summary: Provide interface for cch Runners.
Author: Daniele Tentoni
Author-email: daniele.tentoni.1996@gmail.com
Requires-Python: >=3.10,<4.0
Classifier: Programming Language :: Python :: 3
Classifier: Programming Language :: Python :: 3.10
Classifier: Programming Language :: Python :: 3.11
